ipyoptimade/__init__.py
ipyoptimade/default_parameters.py
ipyoptimade/exceptions.py
ipyoptimade/informational.py
ipyoptimade/logger.py
ipyoptimade/query_filter.py
ipyoptimade/query_provider.py
ipyoptimade/summary.py
ipyoptimade/utils.py
ipyoptimade/version.py
ipyoptimade/warnings.py
ipyoptimade/statics/optimade-text-right-transparent-bg.png
ipyoptimade/subwidgets/__init__.py
ipyoptimade/subwidgets/filter_inputs.py
ipyoptimade/subwidgets/intrangeslider.py
ipyoptimade/subwidgets/multi_checkbox.py
ipyoptimade/subwidgets/output_summary.py
ipyoptimade/subwidgets/periodic_table.py
ipyoptimade/subwidgets/provider_database.py
ipyoptimade/subwidgets/results.py
ipyoptimade/subwidgets/sort_selector.py
ipyoptimade-1.2.2.dist-info/licenses/LICENSE
ipyoptimade-1.2.2.dist-info/WHEEL
ipyoptimade-1.2.2.dist-info/METADATA
ipyoptimade-1.2.2.dist-info/RECORD
