Metadata-Version: 2.4
Name: ipyoptimade
Version: 1.2.2
Summary: Jupyter client for searching structures through OPTIMADE API
Author-email: Casper Welzel Andersen <casper+github@welzel.nu>, Kristjan Eimre <kristan.eimre@epfl.ch>, Jusong Yu <jusong.yu@psi.ch>
Requires-Python: >=3.9
Classifier: Development Status :: 5 - Production/Stable
Classifier: Framework :: AiiDA
Classifier: Framework :: Jupyter
Classifier: Intended Audience :: Science/Research
Classifier: License :: OSI Approved :: MIT License
Classifier: Operating System :: MacOS :: MacOS X
Classifier: Operating System :: POSIX :: Linux
Classifier: Operating System :: Microsoft :: Windows
Classifier: Programming Language :: Python :: 3 :: Only
Classifier: Programming Language :: Python :: 3.9
Classifier: Programming Language :: Python :: 3.10
Classifier: Programming Language :: Python :: 3.11
Classifier: Topic :: Database :: Front-Ends
Classifier: Topic :: Scientific/Engineering
Classifier: Topic :: Scientific/Engineering :: Chemistry
Classifier: Topic :: Scientific/Engineering :: Physics
Classifier: Topic :: Software Development :: Widget Sets
License-File: LICENSE
Requires-Dist: appdirs~=1.4.4
Requires-Dist: cachecontrol[filecache]~=0.13.1
Requires-Dist: ipywidgets>=7.6,<9
Requires-Dist: nglview~=3.0.8
Requires-Dist: optimade~=1.0
Requires-Dist: ase~=3.22
Requires-Dist: pandas~=2.1
Requires-Dist: requests~=2.31
Requires-Dist: widget_periodictable~=4.1.3
Requires-Dist: semver~=3.0
Requires-Dist: widget-dropdown~=0.4.1
Requires-Dist: pre-commit~=3.6 ; extra == "dev"
Requires-Dist: pytest~=7.4 ; extra == "dev"
Requires-Dist: pytest-cov~=4.1 ; extra == "dev"
Requires-Dist: bumpver>=2023.1129 ; extra == "dev"
Requires-Dist: pip-tools~=7.4 ; extra == "dev"
Requires-Dist: voila~=0.4.0 ; extra == "voila"
Project-URL: Documentation, https://github.com/aiidalab/ipyoptimade#readme
Project-URL: Source, https://github.com/aiidalab/ipyoptimade
Project-URL: Tracker, https://github.com/aiidalab/ipyoptimade/issues
Provides-Extra: dev
Provides-Extra: voila
